ontogram/__init__.py
ontogram/cli.py
ontogram/curies.py
ontogram-0.1.1.dist-info/entry_points.txt
ontogram-0.1.1.dist-info/LICENSE
ontogram-0.1.1.dist-info/WHEEL
ontogram-0.1.1.dist-info/METADATA
ontogram-0.1.1.dist-info/RECORD
