Metadata-Version: 2.1
Name: ontogram
Version: 0.1.1
Summary: Ontogram - an OWL ontology diagram generator.
Home-page: https://github.com/edmondchuc/ontogram
License: MIT
Author: Edmond Chuc
Author-email: edmond.chuc@gmail.com
Requires-Python: >=3.7,<4.0
Classifier: Intended Audience :: Developers
Classifier: License :: OSI Approved :: GNU General Public License v3 or later (GPLv3+)
Classifier: License :: OSI Approved :: MIT License
Classifier: Natural Language :: English
Classifier: Programming Language :: Python :: 3
Classifier: Programming Language :: Python :: 3.7
Classifier: Programming Language :: Python :: 3.8
Classifier: Programming Language :: Python :: 3.9
Classifier: Programming Language :: Python :: 3.10
Classifier: Programming Language :: Python :: 3
Classifier: Programming Language :: Python :: 3 :: Only
Classifier: Programming Language :: Python :: 3.7
Classifier: Programming Language :: Python :: Implementation :: CPython
Classifier: Programming Language :: Python :: Implementation :: PyPy
Classifier: Topic :: Software Development :: Libraries :: Python Modules
Classifier: Topic :: Utilities
Requires-Dist: click (>=8.1.3,<9.0.0)
Requires-Dist: plantuml (>=0.3.0,<0.4.0)
Requires-Dist: rdflib (>=6.2.0,<7.0.0)
Project-URL: Repository, https://github.com/edmondchuc/ontogram
